dophon_cloud_center/__init__.py
dophon_cloud_center/kits/__init__.py
dophon_cloud_center/reg_center.py
dophon_cloud_center/templates/center.html
dophon_cloud_center-1.0.1.dist-info/WHEEL
dophon_cloud_center-1.0.1.dist-info/METADATA
dophon_cloud_center-1.0.1.dist-info/RECORD
