Metadata-Version: 2.1
Name: dophon-cloud-center
Version: 1.0.1
Summary: dophon cloud reg center
Home-page: UNKNOWN
License: UNKNOWN
Author: CallMeE
Author-email: ealohu@163.com
Requires-Python: >=3.6,<4.0
Classifier: Programming Language :: Python :: 3
Classifier: Programming Language :: Python :: 3.6
Classifier: Programming Language :: Python :: 3.7
Requires-Dist: dophon
